setup.cfg
setup.py
fcm/__init__.py
fcm/cli.py
fcm/message_loaders.py
fcm/signatures.py
fcmxz.egg-info/PKG-INFO
fcmxz.egg-info/SOURCES.txt
fcmxz.egg-info/dependency_links.txt
fcmxz.egg-info/entry_points.txt
fcmxz.egg-info/not-zip-safe
fcmxz.egg-info/requires.txt
fcmxz.egg-info/top_level.txt